Workbook

Sheet My Grant
A2: My Option Grant — Modelling Tool
A3: Enter your grant details below (blue cells). Formulas will calculate automatically.
A5: Section 1 — Your Grant Details
A6: Number of Options Granted | B6: 1000 | C6: Enter the total number of options in your grant agreement
A7: Strike Price (per share, CAD $) | B7: 10 | C7: Your exercise price — set out in your grant agreement
A8: Fully Diluted Shares Outstanding | B8: 10000000 | C8: Total shares + options + warrants. Ask your company for this number.
A9: Vesting Period (years) | B9: 4 | C9: Typical: 4 or 5 years
A10: Cliff (years) | B10: 1 | C10: Minimum time before any options vest. Typical: 1 year
A11: Years Since Grant Date | B11: 2 | C11: How long have you been vesting? Use decimals (e.g. 1.5 = 18 months)
A13: Section 2 — Your Grant at a Glance
A14: % of Company You Own (fully diluted) | B14: =B6/B8 -> 0.0001 | C14: Your options ÷ fully diluted shares. This is the number that really matters.
A15: Options Vested To Date | B15: =IF(B11<B10, 0, IF(B11>=B9, B6, FLOOR((B11/B9)*B6, 1))) -> 500 | C15: 0 before cliff; pro-rated monthly after cliff; full grant at end of vesting period
A16: Options Still Unvested | B16: =B6-B15 -> 500 | C16: Options you'd forfeit if you left today
A17: % Vested | B17: =IF(B6=0,0,B15/B6) -> 0.5
A19: Section 3 — Quick Value Snapshot
A20: Hypothetical Current Share Price (CAD $) | B20: 10 | C20: Enter a share price — try your last round price, or a hypothetical exit price
A21: Value of Vested Options (pre-tax) | B21: =MAX(0,(B20-B7)*B15) -> 0 | C21: (Share price minus Strike price) x Vested options. Zero if underwater.
A22: Value of Full Grant if Fully Vested (pre-tax) | B22: =MAX(0,(B20-B7)*B6) -> 0 | C22: What your full grant would be worth if you were 100% vested at this price
A23: Implied Company Valuation at This Price | B23: =B20*B8 -> 100000000 | C23: Share price × fully diluted shares = implied total company value
A25: ⚠ These figures are pre-tax estimates only. Actual proceeds depend on deal structure, tax treatment, and your specific grant terms. Consult a tax advisor before making any exercise decisions.

Sheet Scenario Modeller
A2: Scenario Modeller — What Could My Options Be Worth?
A3: This sheet pulls your grant details from 'My Grant'. Adjust the exit valuations below (blue) to explore different outcomes.
A5: Your Grant (from My Grant sheet)
A6: Options Granted | B6: ='My Grant'!B6 -> 1000
A7: Strike Price (CAD $) | B7: ='My Grant'!B7 -> 10
A8: Fully Diluted Shares | B8: ='My Grant'!B8 -> 10000000
A9: % Ownership | B9: ='My Grant'!B14 -> 0.0001
A10: Vested Options | B10: ='My Grant'!B15 -> 500
A12: Exit Scenario Modeller
A13: Scenario | B13: Company Valuation (CAD $) | C13: Implied Share Price | D13: Gain per Option | E13: Value of Vested Options | F13: Value of Full Grant | G13: Multiple on Strike Price
A14: Base — Last Round | B14: ='My Grant'!B8*'My Grant'!B7 -> 100000000 | C14: =B14/'My Grant'!B8 -> 10 | D14: =MAX(0,C14-'My Grant'!B7) -> 0 | E14: =MAX(0,D14*'My Grant'!B15) -> 0 | F14: =MAX(0,D14*'My Grant'!B6) -> 0 | G14: =IF('My Grant'!B7=0,"-",C14/'My Grant'!B7) -> 1
A15: 2x Last Round | B15: ='My Grant'!B8*'My Grant'!B7*2 -> 200000000 | C15: =B15/'My Grant'!B8 -> 20 | D15: =MAX(0,C15-'My Grant'!B7) -> 10 | E15: =MAX(0,D15*'My Grant'!B15) -> 5000 | F15: =MAX(0,D15*'My Grant'!B6) -> 10000 | G15: =IF('My Grant'!B7=0,"-",C15/'My Grant'!B7) -> 2
A16: Conservative Exit | B16: 50000000 | C16: =B16/'My Grant'!B8 -> 5 | D16: =MAX(0,C16-'My Grant'!B7) -> 0 | E16: =MAX(0,D16*'My Grant'!B15) -> 0 | F16: =MAX(0,D16*'My Grant'!B6) -> 0 | G16: =IF('My Grant'!B7=0,"-",C16/'My Grant'!B7) -> 0.5
A17: Moderate Exit | B17: 150000000 | C17: =B17/'My Grant'!B8 -> 15 | D17: =MAX(0,C17-'My Grant'!B7) -> 5 | E17: =MAX(0,D17*'My Grant'!B15) -> 2500 | F17: =MAX(0,D17*'My Grant'!B6) -> 5000 | G17: =IF('My Grant'!B7=0,"-",C17/'My Grant'!B7) -> 1.5
A18: Strong Exit | B18: 500000000 | C18: =B18/'My Grant'!B8 -> 50 | D18: =MAX(0,C18-'My Grant'!B7) -> 40 | E18: =MAX(0,D18*'My Grant'!B15) -> 20000 | F18: =MAX(0,D18*'My Grant'!B6) -> 40000 | G18: =IF('My Grant'!B7=0,"-",C18/'My Grant'!B7) -> 5
A19: Exceptional Exit | B19: 1000000000 | C19: =B19/'My Grant'!B8 -> 100 | D19: =MAX(0,C19-'My Grant'!B7) -> 90 | E19: =MAX(0,D19*'My Grant'!B15) -> 45000 | F19: =MAX(0,D19*'My Grant'!B6) -> 90000 | G19: =IF('My Grant'!B7=0,"-",C19/'My Grant'!B7) -> 10
A20: Custom — Enter Below | B20: 250000000 | C20: =B20/'My Grant'!B8 -> 25 | D20: =MAX(0,C20-'My Grant'!B7) -> 15 | E20: =MAX(0,D20*'My Grant'!B15) -> 7500 | F20: =MAX(0,D20*'My Grant'!B6) -> 15000 | G20: =IF('My Grant'!B7=0,"-",C20/'My Grant'!B7) -> 2.5
A22: Vesting Timeline
A23: Year | B23: Cumulative Vested Options | C23: % Vested | D23: Value at Conservative Exit ($50M) | E23: Value at Strong Exit ($500M)
A24: Year 0 | B24: 0 | C24: =IF('My Grant'!B6=0,0,B24/('My Grant'!B6)) -> 0 | D24: =MAX(0,(50000000/'My Grant'!B8-'My Grant'!B7)*B24) -> 0 | E24: =MAX(0,(500000000/'My Grant'!B8-'My Grant'!B7)*B24) -> 0
A25: Year 1 | B25: =IF(1<'My Grant'!B10,0,IF(1>='My Grant'!B9,'My Grant'!B6,FLOOR((1/'My Grant'!B9)*'My Grant'!B6,1))) -> 250 | C25: =IF('My Grant'!B6=0,0,B25/('My Grant'!B6)) -> 0.25 | D25: =MAX(0,(50000000/'My Grant'!B8-'My Grant'!B7)*B25) -> 0 | E25: =MAX(0,(500000000/'My Grant'!B8-'My Grant'!B7)*B25) -> 10000
A26: Year 2 | B26: =IF(2<'My Grant'!B10,0,IF(2>='My Grant'!B9,'My Grant'!B6,FLOOR((2/'My Grant'!B9)*'My Grant'!B6,1))) -> 500 | C26: =IF('My Grant'!B6=0,0,B26/('My Grant'!B6)) -> 0.5 | D26: =MAX(0,(50000000/'My Grant'!B8-'My Grant'!B7)*B26) -> 0 | E26: =MAX(0,(500000000/'My Grant'!B8-'My Grant'!B7)*B26) -> 20000
A27: Year 3 | B27: =IF(3<'My Grant'!B10,0,IF(3>='My Grant'!B9,'My Grant'!B6,FLOOR((3/'My Grant'!B9)*'My Grant'!B6,1))) -> 750 | C27: =IF('My Grant'!B6=0,0,B27/('My Grant'!B6)) -> 0.75 | D27: =MAX(0,(50000000/'My Grant'!B8-'My Grant'!B7)*B27) -> 0 | E27: =MAX(0,(500000000/'My Grant'!B8-'My Grant'!B7)*B27) -> 30000
A28: Year 4 | B28: =IF(4<'My Grant'!B10,0,IF(4>='My Grant'!B9,'My Grant'!B6,FLOOR((4/'My Grant'!B9)*'My Grant'!B6,1))) -> 1000 | C28: =IF('My Grant'!B6=0,0,B28/('My Grant'!B6)) -> 1 | D28: =MAX(0,(50000000/'My Grant'!B8-'My Grant'!B7)*B28) -> 0 | E28: =MAX(0,(500000000/'My Grant'!B8-'My Grant'!B7)*B28) -> 40000
A29: Year 5 | B29: =IF(5<'My Grant'!B10,0,IF(5>='My Grant'!B9,'My Grant'!B6,FLOOR((5/'My Grant'!B9)*'My Grant'!B6,1))) -> 1000 | C29: =IF('My Grant'!B6=0,0,B29/('My Grant'!B6)) -> 1 | D29: =MAX(0,(50000000/'My Grant'!B8-'My Grant'!B7)*B29) -> 0 | E29: =MAX(0,(500000000/'My Grant'!B8-'My Grant'!B7)*B29) -> 40000
A31: ⚠ Pre-tax estimates only. Does not account for dilution from future financing rounds, liquidation preferences, or exercise costs. Consult a tax and legal advisor for advice specific to your situation.
